fadex/__init__.py
fadex/fadex.py
fadex_exp-0.1.0.dist-info/licenses/LICENSE
fadex_exp-0.1.0.dist-info/METADATA
fadex_exp-0.1.0.dist-info/WHEEL
fadex_exp-0.1.0.dist-info/top_level.txt
fadex_exp-0.1.0.dist-info/RECORD
