Metadata-Version: 2.4
Name: fadex-exp
Version: 0.1.0
Summary: A feature attribution explainability method for dimensionality reduction algorithms.
Home-page: https://github.com/greffao/fadex
Author: Lucas Greff Meneses
Author-email: lucasgreffmeneses@usp.br
Classifier: Programming Language :: Python :: 3
Classifier: License :: OSI Approved :: MIT License
Classifier: Operating System :: OS Independent
Requires-Python: >=3.6
License-File: LICENSE
Requires-Dist: numpy
Requires-Dist: pandas
Requires-Dist: scipy
Requires-Dist: scikit-learn
Requires-Dist: matplotlib
Requires-Dist: plotly
Requires-Dist: tqdm
Provides-Extra: gpu
Requires-Dist: cupy; extra == "gpu"
Requires-Dist: cuml; extra == "gpu"
Dynamic: author
Dynamic: author-email
Dynamic: classifier
Dynamic: description
Dynamic: description-content-type
Dynamic: home-page
Dynamic: license-file
Dynamic: provides-extra
Dynamic: requires-dist
Dynamic: requires-python
Dynamic: summary
